zxlive/__init__.py
zxlive/__main__.py
zxlive/animations.py
zxlive/app.py
zxlive/base_panel.py
zxlive/commands.py
zxlive/common.py
zxlive/construct.py
zxlive/custom_rule.py
zxlive/dialogs.py
zxlive/edit_panel.py
zxlive/editor_base_panel.py
zxlive/eitem.py
zxlive/graphscene.py
zxlive/graphview.py
zxlive/mainwindow.py
zxlive/proof.py
zxlive/proof_panel.py
zxlive/rewrite_action.py
zxlive/rewrite_data.py
zxlive/rule_panel.py
zxlive/settings.py
zxlive/settings_dialog.py
zxlive/sfx.py
zxlive/tikz.py
zxlive/vitem.py
zxlive/icons/folder.svg
zxlive/icons/magic-wand.svg
zxlive/icons/redo.svg
zxlive/icons/tikzit-tool-edge.svg
zxlive/icons/tikzit-tool-node.svg
zxlive/icons/tikzit-tool-select.svg
zxlive/icons/undo.svg
zxlive/icons/vertex-snap-to-edge.svg
zxlive/sfx/boom-boom-boom.wav
zxlive/sfx/iranian-bus.wav
zxlive/sfx/ok-im-gonna-start.wav
zxlive/sfx/thats-a-spider.wav
zxlive/sfx/thats-just-wire-1.wav
zxlive/sfx/thats-just-wire-2.wav
zxlive/sfx/thats-spider-fusion.wav
zxlive/sfx/they-fall-off.wav
zxlive/sfx/welcome-everybody.wav
zxlive/tooltips/bialgebra.png
zxlive/tooltips/copy_pi.png
zxlive/tooltips/gadget_fuse.png
zxlive/tooltips/lcomp.png
zxlive/tooltips/pivot_gadget.png
zxlive/tooltips/pivot_regular.png
zxlive/tooltips/push_pauli.png
zxlive-0.3.0.dist-info/LICENSE
zxlive-0.3.0.dist-info/METADATA
zxlive-0.3.0.dist-info/WHEEL
zxlive-0.3.0.dist-info/entry_points.txt
zxlive-0.3.0.dist-info/top_level.txt
zxlive-0.3.0.dist-info/RECORD
