Metadata-Version: 2.2
Name: zxlive
Version: 0.3.0
Summary: An interactive tool for the ZX-calculus
Author: ZXLive contributors
Author-email: john@vdwetering.name
License:                                  Apache License
Project-URL: Homepage, https://github.com/zxcalc/zxlive
Project-URL: Repository, https://github.com/zxcalc/zxlive
Project-URL: Issue-Tracker, https://github.com/zxcalc/zxlive/issues
Classifier: License :: OSI Approved :: Apache Software License
Classifier: Intended Audience :: Developers
Classifier: Intended Audience :: Science/Research
Classifier: Operating System :: OS Independent
Classifier: Programming Language :: Python :: 3
Classifier: Programming Language :: Python :: 3.9
Classifier: Programming Language :: Python :: 3.10
Classifier: Programming Language :: Python :: 3.11
Classifier: Topic :: Scientific/Engineering
Requires-Python: >=3.9
License-File: LICENSE
Requires-Dist: PySide6>=6.7.2
Requires-Dist: pyzx>=0.9.0
Requires-Dist: networkx
Requires-Dist: numpy
Requires-Dist: shapely
Requires-Dist: pyperclip
Requires-Dist: imageio
Provides-Extra: test
Requires-Dist: mypy; extra == "test"
Requires-Dist: pyproject-flake8; extra == "test"
Requires-Dist: pylint; extra == "test"
Requires-Dist: pytest-qt; extra == "test"
Provides-Extra: doc
Requires-Dist: sphinx<7,>=2.3; extra == "doc"
Requires-Dist: sphinx_autodoc_typehints>=1.10; extra == "doc"
Requires-Dist: sphinx_rtd_theme>=0.4; extra == "doc"
Requires-Dist: sphinxcontrib-svg2pdfconverter>=1.2.2; extra == "doc"
Requires-Dist: myst-parser>=3.0.0; extra == "doc"
